shipment_optimizer/__init__.py
shipment_optimizer/optimizer.py
shipment_optimizer-1.0.0.dist-info/METADATA
shipment_optimizer-1.0.0.dist-info/WHEEL
shipment_optimizer-1.0.0.dist-info/top_level.txt
shipment_optimizer-1.0.0.dist-info/RECORD
