Metadata-Version: 2.1
Name: shipment-optimizer
Version: 1.0.0
Summary: Optimize shipment assignments in logistics projects.
Home-page: https://github.com/yourusername/shipment-optimizer
Author: Your Name
Author-email: your_email@example.com
License: UNKNOWN
Platform: UNKNOWN
Classifier: Programming Language :: Python :: 3
Classifier: License :: OSI Approved :: MIT License
Classifier: Operating System :: OS Independent
